setup.py
replforks/__init__.py
replforks.egg-info/PKG-INFO
replforks.egg-info/SOURCES.txt
replforks.egg-info/dependency_links.txt
replforks.egg-info/top_level.txt