Metadata-Version: 1.0
Name: replforks
Version: 1.0.0
Summary: A way to detect forks in python.
Home-page: UNKNOWN
Author: UNKNOWN
Author-email: UNKNOWN
License: UNKNOWN
Platform: UNKNOWN
